vendor/__about__.py
vendor/__init__.py
vendor/client.py
vendor/service.py
vendor/aws/vendor-deployment.yml
vendor/aws/vendor.yml
vendor/aws/vendor/build.sh
vendor/aws/vendor/handler.py
vendor-0.1.dist-info/DESCRIPTION.rst
vendor-0.1.dist-info/METADATA
vendor-0.1.dist-info/RECORD
vendor-0.1.dist-info/WHEEL
vendor-0.1.dist-info/metadata.json
vendor-0.1.dist-info/top_level.txt
