Metadata-Version: 1.2
Name: vendor
Version: 0.1
Summary: Vendor provides an AWS service API for building binary Python packages for use in Lambda functions.
Home-page: https://github.com/joshringer/python-vendor
Author: Joshua Ringer
Author-email: joshringer@users.noreply.github.com
License: Public Domain
Keywords: aws lambda vendor build binary package wheel
Platform: UNKNOWN
Classifier: Development Status :: 4 - Beta
Classifier: Environment :: Console
Classifier: Intended Audience :: Developers
Classifier: License :: Public Domain
Classifier: Natural Language :: English
Classifier: Operating System :: POSIX
Classifier: Programming Language :: Python
Classifier: Programming Language :: Python :: 2.7
Classifier: Programming Language :: Python :: 3.6
Classifier: Topic :: Software Development
Requires-Python: >=2.7, !=3.0.*, !=3.1.*, !=3.2.*, !=3.3.*, !=3.4.*, !=3.5.*
